rpa_pdf/Converter.py
rpa_pdf/Pdf.py
rpa_pdf/Stamp.py
rpa_pdf/__init__.py
rpa_pdf/common.py
rpa_pdf/exec/SumatraPDF-settings.txt
rpa_pdf/exec/__init__.py
rpa_pdf/exec/docto.exe
rpa_pdf/exec/sumatra.exe
rpa_pdf/exec/EmailConverter/EmailConverter.exe
rpa_pdf/exec/EmailConverter/EmailConverterConsole.exe
rpa_pdf/exec/EmailConverter/emailconverter.jar
rpa_pdf/exec/EmailConverter/unins000.dat
rpa_pdf/exec/EmailConverter/unins000.exe
rpa_pdf/exec/EmailConverter/wkhtmltopdf-source.7z
rpa_pdf/exec/EmailConverter/wkhtmltopdf.exe
rpa_pdf/exec/sumatrapdfcache/b0e771a3f3a269a4fae0380eafc1ced3.png
rpa_pdf/exec/wkhtmltox/bin/libwkhtmltox.a
rpa_pdf/exec/wkhtmltox/bin/wkhtmltoimage.exe
rpa_pdf/exec/wkhtmltox/bin/wkhtmltopdf.exe
rpa_pdf/exec/wkhtmltox/bin/wkhtmltox.dll
rpa_pdf/exec/wkhtmltox/include/wkhtmltox/dllbegin.inc
rpa_pdf/exec/wkhtmltox/include/wkhtmltox/dllend.inc
rpa_pdf/exec/wkhtmltox/include/wkhtmltox/image.h
rpa_pdf/exec/wkhtmltox/include/wkhtmltox/pdf.h
rpa_pdf/fonts/DejaVuMathTeXGyre.ttf
rpa_pdf/fonts/DejaVuSans-Bold.ttf
rpa_pdf/fonts/DejaVuSans-BoldOblique.ttf
rpa_pdf/fonts/DejaVuSans-ExtraLight.ttf
rpa_pdf/fonts/DejaVuSans-Oblique.ttf
rpa_pdf/fonts/DejaVuSans.ttf
rpa_pdf/fonts/DejaVuSansCondensed-Bold.ttf
rpa_pdf/fonts/DejaVuSansCondensed-BoldOblique.ttf
rpa_pdf/fonts/DejaVuSansCondensed-Oblique.ttf
rpa_pdf/fonts/DejaVuSansCondensed.ttf
rpa_pdf/fonts/DejaVuSansMono-Bold.ttf
rpa_pdf/fonts/DejaVuSansMono-BoldOblique.ttf
rpa_pdf/fonts/DejaVuSansMono-Oblique.ttf
rpa_pdf/fonts/DejaVuSansMono.ttf
rpa_pdf/fonts/DejaVuSerif-Bold.ttf
rpa_pdf/fonts/DejaVuSerif-BoldItalic.ttf
rpa_pdf/fonts/DejaVuSerif-Italic.ttf
rpa_pdf/fonts/DejaVuSerif.ttf
rpa_pdf/fonts/DejaVuSerifCondensed-Bold.ttf
rpa_pdf/fonts/DejaVuSerifCondensed-BoldItalic.ttf
rpa_pdf/fonts/DejaVuSerifCondensed-Italic.ttf
rpa_pdf/fonts/DejaVuSerifCondensed.ttf
rpa_pdf-1.1.16.dist-info/licenses/LICENSE
rpa_pdf-1.1.16.dist-info/METADATA
rpa_pdf-1.1.16.dist-info/WHEEL
rpa_pdf-1.1.16.dist-info/top_level.txt
rpa_pdf-1.1.16.dist-info/RECORD
