Metadata-Version: 2.4
Name: rpa-pdf
Version: 1.1.16
Summary: Pdf actions for RPA
Author-email: Grzegorz Ziolo <grzegorz.ziolo@gmail.com>
License: The MIT License (MIT)
Project-URL: Homepage, https://github.com/21010/rpa-pdf
Keywords: rpa,pdf
Classifier: License :: OSI Approved :: MIT License
Classifier: Programming Language :: Python
Classifier: Programming Language :: Python :: 3
Requires-Python: >=3.10
License-File: LICENSE
Requires-Dist: pypdf>=3.15.0
Requires-Dist: fpdf2>=2.7.5
Requires-Dist: python-barcode>=0.15.1
Requires-Dist: Pillow>=9.1.1
Requires-Dist: comtypes>=1.2.0
Requires-Dist: pdfkit>=1.0.0
Provides-Extra: dev
Requires-Dist: black; extra == "dev"
Requires-Dist: bumpver; extra == "dev"
Requires-Dist: isort; extra == "dev"
Requires-Dist: pip-tools; extra == "dev"
Requires-Dist: unitest; extra == "dev"
Dynamic: license-file
